spacekit/__init__.py
spacekit/analyzer/__init__.py
spacekit/analyzer/compute.py
spacekit/analyzer/explore.py
spacekit/analyzer/scan.py
spacekit/analyzer/track.py
spacekit/analyzer/validate.py
spacekit/builder/__init__.py
spacekit/builder/architect.py
spacekit/builder/blueprints.py
spacekit/builder/trained_networks/__init__.py
spacekit/builder/trained_networks/hst_cal.zip
spacekit/builder/trained_networks/jwst_cal.zip
spacekit/builder/trained_networks/svm_align.zip
spacekit/dashboard/__init__.py
spacekit/dashboard/cal/__init__.py
spacekit/dashboard/cal/app.py
spacekit/dashboard/cal/config.py
spacekit/dashboard/cal/eda.py
spacekit/dashboard/cal/eval.py
spacekit/dashboard/cal/index.py
spacekit/dashboard/cal/nodegraph.py
spacekit/dashboard/cal/pred.py
spacekit/dashboard/svm/__init__.py
spacekit/dashboard/svm/app.py
spacekit/dashboard/svm/config.py
spacekit/dashboard/svm/eda.py
spacekit/dashboard/svm/eval.py
spacekit/dashboard/svm/index.py
spacekit/dashboard/svm/pred.py
spacekit/datasets/__init__.py
spacekit/datasets/_base.py
spacekit/datasets/beam.py
spacekit/datasets/meta.py
spacekit/extractor/__init__.py
spacekit/extractor/load.py
spacekit/extractor/radio.py
spacekit/extractor/scrape.py
spacekit/generator/__init__.py
spacekit/generator/augment.py
spacekit/generator/draw.py
spacekit/logger/__init__.py
spacekit/logger/log.py
spacekit/preprocessor/__init__.py
spacekit/preprocessor/encode.py
spacekit/preprocessor/ingest.py
spacekit/preprocessor/prep.py
spacekit/preprocessor/scrub.py
spacekit/preprocessor/transform.py
spacekit/skopes/__init__.py
spacekit/skopes/hst/__init__.py
spacekit/skopes/hst/cal/__init__.py
spacekit/skopes/hst/cal/config.py
spacekit/skopes/hst/cal/predict.py
spacekit/skopes/hst/cal/train.py
spacekit/skopes/hst/cal/validate.py
spacekit/skopes/hst/svm/__init__.py
spacekit/skopes/hst/svm/corrupt.py
spacekit/skopes/hst/svm/predict.py
spacekit/skopes/hst/svm/prep.py
spacekit/skopes/hst/svm/train.py
spacekit/skopes/jwst/__init__.py
spacekit-1.1.3.dist-info/licenses/LICENSE
spacekit-1.1.3.dist-info/METADATA
spacekit-1.1.3.dist-info/WHEEL
spacekit-1.1.3.dist-info/top_level.txt
spacekit-1.1.3.dist-info/RECORD
