Metadata-Version: 2.4
Name: spacekit
Version: 1.1.3
Summary: Astronomical Data Science and Machine Learning Toolkit
Home-page: https://github.com/spacetelescope/spacekit
Author: Ru Keïn
Author-email: rkein@stsci.edu
License: MIT
Project-URL: Source, https://github.com/spacetelescope/spacekit
Project-URL: Documentation, https://spacekit.readthedocs.io
Project-URL: Tracker, https://github.com/spacetelescope/spacekit/issues
Classifier: Intended Audience :: Science/Research
Classifier: Topic :: Scientific/Engineering :: Astronomy
Classifier: License :: OSI Approved :: MIT License
Classifier: Programming Language :: Python :: 3
Classifier: Operating System :: OS Independent
Classifier: Programming Language :: Python :: 3.10
Classifier: Programming Language :: Python :: 3.11
Classifier: Programming Language :: Python :: 3.12
Requires-Python: >=3.10
License-File: LICENSE
Requires-Dist: tensorflow>=2.16.1
Requires-Dist: astropy
Requires-Dist: boto3
Requires-Dist: numpy>=1.22
Requires-Dist: pandas
Requires-Dist: scikit-learn>=1.3.2
Provides-Extra: test
Requires-Dist: pytest; extra == "test"
Requires-Dist: pytest-cov; extra == "test"
Requires-Dist: pytest-profiling; extra == "test"
Requires-Dist: tox; extra == "test"
Requires-Dist: bandit; extra == "test"
Requires-Dist: moto; extra == "test"
Requires-Dist: black; extra == "test"
Requires-Dist: ruff; extra == "test"
Provides-Extra: docs
Requires-Dist: sphinx; extra == "docs"
Requires-Dist: furo; extra == "docs"
Requires-Dist: pydot; extra == "docs"
Requires-Dist: graphviz; extra == "docs"
Requires-Dist: sphinx-automodapi; extra == "docs"
Requires-Dist: numpydoc; extra == "docs"
Requires-Dist: sphinx-autobuild; extra == "docs"
Provides-Extra: x
Requires-Dist: astroquery; extra == "x"
Requires-Dist: matplotlib<4; extra == "x"
Requires-Dist: pydot; extra == "x"
Requires-Dist: graphviz; extra == "x"
Requires-Dist: plotly; extra == "x"
Requires-Dist: progressbar; extra == "x"
Requires-Dist: scikeras; extra == "x"
Requires-Dist: tables; extra == "x"
Requires-Dist: tqdm; extra == "x"
Dynamic: license-file
